chocolatine/__init__.py
chocolatine/agg_function.py
chocolatine/alter_mode.py
chocolatine/join_type.py
chocolatine/operator.py
chocolatine/ordering.py
chocolatine/query_mode.py
chocolatine/shortcut.py
chocolatine/sql_function.py
chocolatine/sql_type.py
chocolatine/utils.py
chocolatine/view_mode.py
chocolatine/expr/__init__.py
chocolatine/expr/col.py
chocolatine/expr/col_when.py
chocolatine/expr/condition.py
chocolatine/expr/delete.py
chocolatine/expr/delete_from.py
chocolatine/expr/from_expr.py
chocolatine/expr/group_by.py
chocolatine/expr/having.py
chocolatine/expr/join.py
chocolatine/expr/limit.py
chocolatine/expr/order_by.py
chocolatine/expr/query.py
chocolatine/expr/select.py
chocolatine/expr/select_from.py
chocolatine/expr/set.py
chocolatine/expr/table.py
chocolatine/expr/union.py
chocolatine/expr/update.py
chocolatine/expr/update_set.py
chocolatine/expr/view.py
chocolatine/expr/when.py
chocolatine/expr/where.py
chocolatine-0.89.9.dist-info/LICENSE
chocolatine-0.89.9.dist-info/METADATA
chocolatine-0.89.9.dist-info/WHEEL
chocolatine-0.89.9.dist-info/top_level.txt
chocolatine-0.89.9.dist-info/RECORD
