Metadata-Version: 2.1
Name: chocolatine
Version: 0.89.9
Summary: Dynamic generation of SQL queries
Home-page: https://github.com/pe-brian/chocolatine
Author: Pierre-Emmanuel Brian
Author-email: pebrian@outlook.fr
Project-URL: Bug Tracker, https://github.com/pe-brian/chocolatine/issues
Classifier: Programming Language :: Python :: 3
Classifier: License :: OSI Approved :: MIT License
Classifier: Operating System :: OS Independent
Requires-Python: >=3.12.2
License-File: LICENSE
Requires-Dist: typeguard ==4.3.0
Requires-Dist: choc-expr ==1.3.5
